package_mchalitsios/__init__.py
package_mchalitsios/telemetry_kit/Observer.py
package_mchalitsios/telemetry_kit/Resource.py
package_mchalitsios/telemetry_kit/__init__.py
package_mchalitsios/telemetry_kit/refactor.py
package_mchalitsios/telemetry_kit/utils/__init__.py
package_mchalitsios/telemetry_kit/utils/logger.py
package_mchalitsios-1.0.0.dist-info/LICENSE
package_mchalitsios-1.0.0.dist-info/METADATA
package_mchalitsios-1.0.0.dist-info/WHEEL
package_mchalitsios-1.0.0.dist-info/RECORD
