Metadata-Version: 2.1
Name: package_mchalitsios
Version: 1.0.0
Summary: A package that uses the OpenTelemetry SDK to build for other services that need to onboard using OpenTelemetry
Home-page: https://git.eogresources.com/eog/telemetry-py
License: eog
Author: Max Chalitsios
Author-email: Max_Chalitsios@eogresources.com
Requires-Python: >=3.12,<4.0
Classifier: License :: Other/Proprietary License
Classifier: Programming Language :: Python :: 3
Classifier: Programming Language :: Python :: 3.12
Requires-Dist: annotated-types (==0.7.0)
Requires-Dist: anyio (==4.4.0)
Requires-Dist: certifi (==2024.7.4)
Requires-Dist: click (==8.1.7)
Requires-Dist: ddtrace (>=2.9.2,<3.0.0)
Requires-Dist: dnspython (==2.6.1)
Requires-Dist: email-validator (==2.2.0)
Requires-Dist: fastapi (==0.111.0)
Requires-Dist: fastapi-cli (==0.0.4)
Requires-Dist: h11 (==0.14.0)
Requires-Dist: httpcore (==1.0.5)
Requires-Dist: httptools (==0.6.1)
Requires-Dist: httpx (==0.27.0)
Requires-Dist: idna (==3.7)
Requires-Dist: jinja2 (==3.1.4)
Requires-Dist: markdown-it-py (==3.0.0)
Requires-Dist: markupsafe (==2.1.5)
Requires-Dist: mdurl (==0.1.2)
Requires-Dist: opentelemetry-api (>=1.25.0,<2.0.0)
Requires-Dist: opentelemetry-distro (>=0.46b0,<0.47)
Requires-Dist: opentelemetry-instrumentation-aio-pika (>=0.46b0,<0.47)
Requires-Dist: opentelemetry-instrumentation-asgi (>=0.46b0,<0.47)
Requires-Dist: opentelemetry-instrumentation-asyncio (>=0.46b0,<0.47)
Requires-Dist: opentelemetry-instrumentation-confluent-kafka (>=0.46b0,<0.47)
Requires-Dist: opentelemetry-instrumentation-kafka-python (>=0.46b0,<0.47)
Requires-Dist: opentelemetry-instrumentation-mysql (>=0.46b0,<0.47)
Requires-Dist: opentelemetry-instrumentation-mysqlclient (>=0.46b0,<0.47)
Requires-Dist: opentelemetry-instrumentation-psycopg (>=0.46b0,<0.47)
Requires-Dist: opentelemetry-instrumentation-psycopg2 (>=0.46b0,<0.47)
Requires-Dist: opentelemetry-instrumentation-pymemcache (>=0.46b0,<0.47)
Requires-Dist: opentelemetry-instrumentation-pymongo (>=0.46b0,<0.47)
Requires-Dist: opentelemetry-instrumentation-pymysql (>=0.46b0,<0.47)
Requires-Dist: opentelemetry-instrumentation-redis (>=0.46b0,<0.47)
Requires-Dist: opentelemetry-instrumentation-requests (>=0.46b0,<0.47)
Requires-Dist: opentelemetry-instrumentation-sqlalchemy (>=0.46b0,<0.47)
Requires-Dist: opentelemetry-instrumentation-sqlite3 (>=0.46b0,<0.47)
Requires-Dist: opentelemetry-instrumentation-starlette (>=0.46b0,<0.47)
Requires-Dist: opentelemetry-instrumentation-system-metrics (>=0.46b0,<0.47)
Requires-Dist: opentelemetry-instrumentation-threading (>=0.46b0,<0.47)
Requires-Dist: opentelemetry-instrumentation-urllib3 (>=0.46b0,<0.47)
Requires-Dist: opentelemetry-instrumentation-wsgi (>=0.46b0,<0.47)
Requires-Dist: opentelemetry-sdk (>=1.25.0,<2.0.0)
Requires-Dist: orjson (==3.10.6)
Requires-Dist: pydantic (==2.8.2)
Requires-Dist: pydantic-core (==2.20.1)
Requires-Dist: pygments (==2.18.0)
Requires-Dist: python-dotenv (==1.0.1)
Requires-Dist: python-multipart (==0.0.9)
Requires-Dist: pyyaml (==6.0.1)
Requires-Dist: rich (==13.7.1)
Requires-Dist: shellingham (==1.5.4)
Requires-Dist: sniffio (==1.3.1)
Requires-Dist: starlette (==0.37.2)
Requires-Dist: typer (==0.12.3)
Requires-Dist: typing-extensions (==4.12.2)
Requires-Dist: ujson (==5.10.0)
Requires-Dist: uvicorn (==0.30.1)
Requires-Dist: uvloop (==0.19.0)
Requires-Dist: watchfiles (==0.22.0)
Requires-Dist: websockets (==12.0)
Project-URL: Repository, https://git.eogresources.com/eog/telemetry-py
